diffpy/__init__.py
diffpy/snmf/__init__.py
diffpy/snmf/containers.py
diffpy/snmf/factorizers.py
diffpy/snmf/io.py
diffpy/snmf/optimizers.py
diffpy/snmf/polynomials.py
diffpy/snmf/stretchednmfapp.py
diffpy/snmf/subroutines.py
diffpy/snmf/version.py
diffpy.snmf-0.1.3.dist-info/AUTHORS.rst
diffpy.snmf-0.1.3.dist-info/LICENSE.rst
diffpy.snmf-0.1.3.dist-info/METADATA
diffpy.snmf-0.1.3.dist-info/WHEEL
diffpy.snmf-0.1.3.dist-info/top_level.txt
diffpy.snmf-0.1.3.dist-info/RECORD
